{
	"Generated": "2026-05-26T21:12:22.075Z",
	"Mode": "module",
	"GitHubOrg": "fable-retold",
	"DefaultBranch": "master",
	"Module": {
		"Name": "fable-log-logger-bunyan",
		"Repo": "fable-log-logger-bunyan",
		"Group": "",
		"Branch": "master",
		"HasDocs": true,
		"HasCover": true,
		"Sidebar": [
			{
				"Title": "Getting Started",
				"Children": [
					{
						"Title": "Overview",
						"Path": "README.md"
					},
					{
						"Title": "API Reference",
						"Path": "api.md"
					}
				]
			},
			{
				"Title": "Retold Ecosystem",
				"Children": [
					{
						"Title": "Fable",
						"Path": "https://fable-retold.github.io/fable/README.md"
					},
					{
						"Title": "Fable-Log",
						"Path": "https://fable-retold.github.io/fable-log/README.md"
					},
					{
						"Title": "Fable-ServiceProviderBase",
						"Path": "https://fable-retold.github.io/fable-serviceproviderbase/README.md"
					},
					{
						"Title": "Fable-Settings",
						"Path": "https://fable-retold.github.io/fable-settings/README.md"
					}
				]
			}
		],
		"DocFiles": [
			".nojekyll",
			"README.md",
			"_brand.json",
			"_cover.md",
			"_sidebar.md",
			"_topbar.md",
			"_version.json",
			"api.md",
			"index.html",
			"retold-catalog.json",
			"retold-keyword-index.json"
		]
	},
	"Groups": []
}